firefly_iaaa/__init__.py
firefly_iaaa/application/__init__.py
firefly_iaaa/application/container.py
firefly_iaaa/application/api/__init__.py
firefly_iaaa/application/api/authorization_request.py
firefly_iaaa/application/api/change_password.py
firefly_iaaa/application/api/create_token.py
firefly_iaaa/application/api/generic_endpoint.py
firefly_iaaa/application/api/generic_oauth_endpoint.py
firefly_iaaa/application/api/generic_oauth_iam_endpoint.py
firefly_iaaa/application/api/introspect_token.py
firefly_iaaa/application/api/make_client.py
firefly_iaaa/application/api/oauth_login.py
firefly_iaaa/application/api/oauth_register.py
firefly_iaaa/application/api/remove_user.py
firefly_iaaa/application/api/reset_password.py
firefly_iaaa/application/api/revoke_token.py
firefly_iaaa/application/middleware/__init__.py
firefly_iaaa/application/middleware/authentication/__init__.py
firefly_iaaa/application/middleware/authentication/oauth_authenticator.py
firefly_iaaa/application/middleware/authorization/__init__.py
firefly_iaaa/application/middleware/authorization/oauth_authorization.py
firefly_iaaa/application/service/__init__.py
firefly_iaaa/application/service/add_role_to_user.py
firefly_iaaa/application/service/authorize_request.py
firefly_iaaa/application/service/decode_token.py
firefly_iaaa/application/service/get_token_access_rights.py
firefly_iaaa/application/service/make_new_client_or_user.py
firefly_iaaa/application/service/remove_role_from_user.py
firefly_iaaa/domain/__init__.py
firefly_iaaa/domain/error.py
firefly_iaaa/domain/entity/__init__.py
firefly_iaaa/domain/entity/authorization_code.py
firefly_iaaa/domain/entity/bearer_token.py
firefly_iaaa/domain/entity/claim.py
firefly_iaaa/domain/entity/client.py
firefly_iaaa/domain/entity/cohort.py
firefly_iaaa/domain/entity/grant.py
firefly_iaaa/domain/entity/group.py
firefly_iaaa/domain/entity/role.py
firefly_iaaa/domain/entity/scope.py
firefly_iaaa/domain/entity/tenant.py
firefly_iaaa/domain/entity/user.py
firefly_iaaa-0.1.24.dist-info/COPYING
firefly_iaaa-0.1.24.dist-info/METADATA
firefly_iaaa-0.1.24.dist-info/WHEEL
firefly_iaaa-0.1.24.dist-info/top_level.txt
firefly_iaaa-0.1.24.dist-info/RECORD
