Metadata-Version: 2.1
Name: firefly-iaaa
Version: 0.1.24
Summary: Bounded context for users of your application.
Home-page: https://github.com/firefly-framework/firefly-iaaa
Author: JD Williams
Author-email: me@jdwilliams.xyz
License: UNKNOWN
Platform: UNKNOWN
Classifier: Programming Language :: Python :: 3.7
Classifier: Operating System :: OS Independent
Requires-Dist: bcrypt (>=3.1.7)
Requires-Dist: firefly-framework (>=1.2.9)
Requires-Dist: firefly-aws (>=1.2.6)
Requires-Dist: oauthlib (>=3.1.1)
Requires-Dist: PyJWT[crypto] (>=2.1.0)
Provides-Extra: aws_cognito_support
Requires-Dist: firefly-aws (>=1.1.0) ; extra == 'aws_cognito_support'
